omdc/__init__.py
openmetadata_catalog-0.0.1.dist-info/METADATA
openmetadata_catalog-0.0.1.dist-info/WHEEL
openmetadata_catalog-0.0.1.dist-info/top_level.txt
openmetadata_catalog-0.0.1.dist-info/RECORD
