Metadata-Version: 2.4
Name: openmetadata_catalog
Version: 0.0.1
Summary: DataGovernance using Agentic AI
Author-email: Nitin Keshav <nitin.keshav11@gmail.com>
License: MIT
Keywords: one,two
Classifier: Programming Language :: Python :: 3
Requires-Python: >=3.7
Requires-Dist: requests
Requires-Dist: importlib-metadata; python_version < "3.13"
Provides-Extra: test
Requires-Dist: pytest; extra == "test"
Requires-Dist: pytest-cov; extra == "test"
Provides-Extra: release
Requires-Dist: build; extra == "release"
Requires-Dist: twine; extra == "release"
Provides-Extra: static-code-qa
Requires-Dist: pre-commit; extra == "static-code-qa"
Requires-Dist: pylint; extra == "static-code-qa"
Requires-Dist: black; extra == "static-code-qa"
Requires-Dist: isort; extra == "static-code-qa"
Requires-Dist: flake8; extra == "static-code-qa"
Requires-Dist: flake8-docstrings; extra == "static-code-qa"
Requires-Dist: Flake8-pyproject; extra == "static-code-qa"
Requires-Dist: radon; extra == "static-code-qa"
Provides-Extra: dev
Requires-Dist: openmetadata_catalog[release,static-code-qa,test]; extra == "dev"
